sandwich/__init__.py
sandwich/dialects/__init__.py
sandwich/dialects/base.py
sandwich/dialects/ddl_mssql.py
sandwich/dialects/ddl_postgres.py
sandwich/dialects/factory.py
sandwich/dialects/mssql.py
sandwich/dialects/postgres.py
sandwich/dialects/utils.py
sandwich/dv2_helper.py
sandwich/errors.py
sandwich/main.py
sandwich/modeling/__init__.py
sandwich/py.typed
sandwich/strategies/__init__.py
sandwich/strategies/base.py
sandwich/strategies/factory.py
sandwich/strategies/link2fact.py
sandwich/strategies/scd2dim.py
sandwich-0.2.2.dist-info/WHEEL
sandwich-0.2.2.dist-info/entry_points.txt
sandwich-0.2.2.dist-info/METADATA
sandwich-0.2.2.dist-info/RECORD
