Metadata-Version: 2.3
Name: sandwich
Version: 0.2.2
Summary: DataVault 2.0 code gen
Keywords: DWH,Data Vault 2.0
Author: Andrey Morozov
Author-email: Andrey Morozov <andrey@morozov.lv>
Classifier: Programming Language :: Python :: 3
Classifier: License :: OSI Approved :: MIT License
Classifier: Topic :: Database
Classifier: Operating System :: OS Independent
Classifier: Environment :: Console
Classifier: Development Status :: 2 - Pre-Alpha
Classifier: Intended Audience :: Developers
Classifier: Typing :: Typed
Requires-Dist: sqlalchemy
Requires-Python: >=3.14
